pyncentral/NCentralClient.py
pyncentral/__init__.py
pyncentral/__main__.py
pyncentral/exceptions.py
pyncentral-0.0.0.4.dist-info/LICENSE
pyncentral-0.0.0.4.dist-info/METADATA
pyncentral-0.0.0.4.dist-info/WHEEL
pyncentral-0.0.0.4.dist-info/entry_points.txt
pyncentral-0.0.0.4.dist-info/top_level.txt
pyncentral-0.0.0.4.dist-info/RECORD
